{
    "character":  "jamie",
    "label":  "杰米",
    "generatedAt":  "2026-03-30T14:51:32Z",
    "rows":  [
                 {
                     "section":  "Normal Moves",
                     "officialId":  "100",
                     "moveName":  "Standing Light Punch",
                     "moveNameJa":  "立ち弱P（杯打）",
                     "command":  "LP",
                     "commandModern":  "弱",
                     "startup":  "5",
                     "active":  "5-6",
                     "recovery":  "7",
                     "onHit":  "5",
                     "onBlock":  "0",
                     "cancel":  "SPECIAL_MOVE, D_RUSH_CANCEL",
                     "damage":  "300",
                     "property":  "上",
                     "notes":  ""
                 },
                 {
                     "section":  "Normal Moves",
                     "officialId":  "101",
                     "moveName":  "Standing Light Kick",
                     "moveNameJa":  "立ち弱K（頂奏）",
                     "command":  "LK",
                     "commandModern":  "",
                     "startup":  "5",
                     "active":  "5-6",
                     "recovery":  "11",
                     "onHit":  "3",
                     "onBlock":  "-1",
                     "cancel":  "SPECIAL_MOVE, D_RUSH_CANCEL, R_CANCEL_stand_1",
                     "damage":  "300",
                     "property":  "上",
                     "notes":  "連打キャンセル対応"
                 },
                 {
                     "section":  "Normal Moves",
                     "officialId":  "102",
                     "moveName":  "Standing Medium Punch",
                     "moveNameJa":  "立ち中P（背束拳）",
                     "command":  "MP",
                     "commandModern":  "中",
                     "startup":  "8",
                     "active":  "8-11",
                     "recovery":  "14",
                     "onHit":  "6",
                     "onBlock":  "2",
                     "cancel":  "",
                     "damage":  "600",
                     "property":  "上",
                     "notes":  ""
                 },
                 {
                     "section":  "Normal Moves",
                     "officialId":  "103",
                     "moveName":  "Standing Medium Kick",
                     "moveNameJa":  "立ち中K（瞬歩脚）",
                     "command":  "MK",
                     "commandModern":  "AUTO＋中",
                     "startup":  "9",
                     "active":  "9-11",
                     "recovery":  "17",
                     "onHit":  "2",
                     "onBlock":  "-3",
                     "cancel":  "SPECIAL_MOVE, D_RUSH_CANCEL",
                     "damage":  "600",
                     "property":  "上",
                     "notes":  "空振り時硬直1F増加"
                 },
                 {
                     "section":  "Normal Moves",
                     "officialId":  "104",
                     "moveName":  "Standing Heavy Punch",
                     "moveNameJa":  "立ち強P（連發拳）",
                     "command":  "HP",
                     "commandModern":  "強",
                     "startup":  "5",
                     "active":  "5, 7, 12-14",
                     "recovery":  "20",
                     "onHit":  "1",
                     "onBlock":  "-3",
                     "cancel":  "SPECIAL_MOVE_5HP, D_RUSH_CANCEL",
                     "damage":  "900",
                     "property":  "上",
                     "notes":  "持続の1F目までキャンセル可 / 空中ヒット時吹き飛びやられ"
                 },
                 {
                     "section":  "Normal Moves",
                     "officialId":  "105",
                     "moveName":  "Standing Heavy Kick",
                     "moveNameJa":  "立ち強K（魔霞弧）",
                     "command":  "HK",
                     "commandModern":  "AUTO＋強",
                     "startup":  "15",
                     "active":  "15-17",
                     "recovery":  "21",
                     "onHit":  "3",
                     "onBlock":  "-5",
                     "cancel":  "SPECIAL_MOVE, D_RUSH_CANCEL",
                     "damage":  "800",
                     "property":  "上",
                     "notes":  "パニッシュカウンター時膝くずれ / 空中ヒット時吹き飛びやられ"
                 },
                 {
                     "section":  "Normal Moves",
                     "officialId":  "106",
                     "moveName":  "Crouching Light Punch",
                     "moveNameJa":  "しゃがみ弱P（杯打）",
                     "command":  "2 + LP",
                     "commandModern":  "2＋弱",
                     "startup":  "4",
                     "active":  "4-5",
                     "recovery":  "9",
                     "onHit":  "5",
                     "onBlock":  "-1",
                     "cancel":  "SPECIAL_MOVE, D_RUSH_CANCEL, R_CANCEL_crouch_1",
                     "damage":  "250",
                     "property":  "上",
                     "notes":  "連打キャンセル対応"
                 },
                 {
                     "section":  "Normal Moves",
                     "officialId":  "107",
                     "moveName":  "Crouching Light Kick",
                     "moveNameJa":  "しゃがみ弱K（先歩）",
                     "command":  "2 + LK",
                     "commandModern":  "AUTO＋弱",
                     "startup":  "5",
                     "active":  "5-6",
                     "recovery":  "11",
                     "onHit":  "3",
                     "onBlock":  "-3",
                     "cancel":  "R_CANCEL_crouch_1, sporty_2LK_RC",
                     "damage":  "200",
                     "property":  "下",
                     "notes":  "連打キャンセル対応"
                 },
                 {
                     "section":  "Normal Moves",
                     "officialId":  "108",
                     "moveName":  "Crouching Medium Punch",
                     "moveNameJa":  "しゃがみ中P（透骨拳）",
                     "command":  "2 + MP",
                     "commandModern":  "",
                     "startup":  "6",
                     "active":  "6-8",
                     "recovery":  "13",
                     "onHit":  "5",
                     "onBlock":  "-1",
                     "cancel":  "SPECIAL_MOVE, D_RUSH_CANCEL",
                     "damage":  "600",
                     "property":  "上",
                     "notes":  "空振り時硬直2F増加"
                 },
                 {
                     "section":  "Normal Moves",
                     "officialId":  "109",
                     "moveName":  "Crouching Medium Kick",
                     "moveNameJa":  "しゃがみ中K（膝降蹴）",
                     "command":  "2 + MK",
                     "commandModern":  "2＋中",
                     "startup":  "7",
                     "active":  "7-9",
                     "recovery":  "18",
                     "onHit":  "-1",
                     "onBlock":  "-6",
                     "cancel":  "SPECIAL_MOVE, D_RUSH_CANCEL",
                     "damage":  "500",
                     "property":  "下",
                     "notes":  ""
                 },
                 {
                     "section":  "Normal Moves",
                     "officialId":  "110",
                     "moveName":  "Crouching Heavy Punch",
                     "moveNameJa":  "しゃがみ強P（月穿）",
                     "command":  "2 + HP",
                     "commandModern":  "2＋強",
                     "startup":  "8",
                     "active":  "8-12",
                     "recovery":  "23",
                     "onHit":  "0",
                     "onBlock":  "-8",
                     "cancel":  "SPECIAL_MOVE, D_RUSH_CANCEL",
                     "damage":  "900",
                     "property":  "上",
                     "notes":  "強制立ち効果 / 持続の2F目までキャンセル可"
                 },
                 {
                     "section":  "Normal Moves",
                     "officialId":  "111",
                     "moveName":  "Crouching Heavy Kick",
                     "moveNameJa":  "しゃがみ強K（始廻）",
                     "command":  "2 + HK",
                     "commandModern":  "",
                     "startup":  "9",
                     "active":  "9-10, 13-15",
                     "recovery":  "28",
                     "onHit":  "D",
                     "onBlock":  "-11",
                     "cancel":  "Nomal_Zurasi_Cancel",
                     "damage":  "800",
                     "property":  "※下",
                     "notes":  "パニッシュカウンター時ダウン時間増加、ハードノックダウン / 空中ヒット時吹き飛びやられ / ※ガード時硬直1F増加 / ※初段がガード時のみ2段目が上段判定"
                 },
                 {
                     "section":  "Normal Moves",
                     "officialId":  "112",
                     "moveName":  "Jumping Light Punch",
                     "moveNameJa":  "ジャンプ弱P（裏肘落）",
                     "command":  "（ジャンプ中に）LP",
                     "commandModern":  "（ジャンプ中に）AUTO + 弱",
                     "startup":  "5",
                     "active":  "5-13",
                     "recovery":  "着地後3",
                     "onHit":  "",
                     "onBlock":  "",
                     "cancel":  "",
                     "damage":  "300",
                     "property":  "中",
                     "notes":  "めくり性能"
                 },
                 {
                     "section":  "Normal Moves",
                     "officialId":  "113",
                     "moveName":  "Jumping Light Kick",
                     "moveNameJa":  "ジャンプ弱K（麓刺）",
                     "command":  "（ジャンプ中に）LK",
                     "commandModern":  "（ジャンプ中に）弱",
                     "startup":  "6",
                     "active":  "6-11",
                     "recovery":  "着地後3",
                     "onHit":  "",
                     "onBlock":  "",
                     "cancel":  "",
                     "damage":  "300",
                     "property":  "中",
                     "notes":  ""
                 },
                 {
                     "section":  "Normal Moves",
                     "officialId":  "114",
                     "moveName":  "Jumping Medium Punch",
                     "moveNameJa":  "ジャンプ中P（雲掴）",
                     "command":  "（ジャンプ中に）MP",
                     "commandModern":  "（ジャンプ中に）中",
                     "startup":  "7",
                     "active":  "7-10",
                     "recovery":  "着地後3",
                     "onHit":  "",
                     "onBlock":  "",
                     "cancel":  "AIR_MUEISHU",
                     "damage":  "700",
                     "property":  "中",
                     "notes":  "空中ヒット時吹き飛びやられ"
                 },
                 {
                     "section":  "Normal Moves",
                     "officialId":  "115",
                     "moveName":  "Jumping Medium Kick",
                     "moveNameJa":  "ジャンプ中K（飛燕腿）",
                     "command":  "（ジャンプ中に）MK",
                     "commandModern":  "（ジャンプ中に）AUTO + 中",
                     "startup":  "7",
                     "active":  "7-12",
                     "recovery":  "着地後3",
                     "onHit":  "",
                     "onBlock":  "",
                     "cancel":  "",
                     "damage":  "500",
                     "property":  "中",
                     "notes":  "めくり性能"
                 },
                 {
                     "section":  "Normal Moves",
                     "officialId":  "116",
                     "moveName":  "Jumping Heavy Punch",
                     "moveNameJa":  "ジャンプ強P（鞭槌打）",
                     "command":  "（ジャンプ中に）HP",
                     "commandModern":  "（ジャンプ中に）AUTO + 強",
                     "startup":  "10",
                     "active":  "10-15",
                     "recovery":  "着地後3",
                     "onHit":  "",
                     "onBlock":  "",
                     "cancel":  "",
                     "damage":  "800",
                     "property":  "中",
                     "notes":  "空中ヒット時叩きつけダウン"
                 },
                 {
                     "section":  "Normal Moves",
                     "officialId":  "117",
                     "moveName":  "Jumping Heavy Kick",
                     "moveNameJa":  "ジャンプ強K（連空腿）",
                     "command":  "（ジャンプ中に）HK",
                     "commandModern":  "（ジャンプ中に）強",
                     "startup":  "8",
                     "active":  "8-10, 16-19",
                     "recovery":  "着地後3",
                     "onHit":  "",
                     "onBlock":  "",
                     "cancel":  "",
                     "damage":  "800",
                     "property":  "中中",
                     "notes":  "空中ヒット時吹き飛びやられ"
                 },
                 {
                     "section":  "Unique Attacks",
                     "officialId":  "200",
                     "moveName":  "Tensei Kick",
                     "moveNameJa":  "天晴脚",
                     "command":  "2 + LKMKHK",
                     "commandModern":  "2＋中強",
                     "startup":  "9",
                     "active":  "9-11",
                     "recovery":  "22",
                     "onHit":  "D",
                     "onBlock":  "-8",
                     "cancel":  "2KK_C_Jump",
                     "damage":  "600",
                     "property":  "上",
                     "notes":  "ヒット時のみジャンプキャンセル可能"
                 },
                 {
                     "section":  "Unique Attacks",
                     "officialId":  "201",
                     "moveName":  "Shikai Kick",
                     "moveNameJa":  "始廻",
                     "command":  "",
                     "commandModern":  "3＋強",
                     "startup":  "9",
                     "active":  "9-10, 13-15",
                     "recovery":  "28",
                     "onHit":  "D",
                     "onBlock":  "-11",
                     "cancel":  "Nomal_Zurasi_Cancel",
                     "damage":  "800",
                     "property":  "※下",
                     "notes":  "パニッシュカウンター時ダウン時間増加、ハードノックダウン / 空中ヒット時吹き飛びやられ / ※ガード時硬直1F増加 / ※初段がガード時のみ2段目が上段判定"
                 },
                 {
                     "section":  "Unique Attacks",
                     "officialId":  "202",
                     "moveName":  "Phantom Sway(2)",
                     "moveNameJa":  "幻酔舞（2段目）",
                     "command":  "2+HK\u003eHK",
                     "commandModern":  "3＋強＞強",
                     "startup":  "12",
                     "active":  "12-14",
                     "recovery":  "43",
                     "onHit":  "D",
                     "onBlock":  "-28",
                     "cancel":  "2HK_HK_P",
                     "damage":  "500",
                     "property":  "上",
                     "notes":  ""
                 },
                 {
                     "section":  "Unique Attacks",
                     "officialId":  "203",
                     "moveName":  "Phantom Sway(3)",
                     "moveNameJa":  "幻酔舞（3段目）",
                     "command":  "2+HK\u003eHK\u003eLP | MP | HP",
                     "commandModern":  "3＋強＞強＞強",
                     "startup":  "",
                     "active":  "",
                     "recovery":  "",
                     "onHit":  "",
                     "onBlock":  "",
                     "cancel":  "",
                     "damage":  "0",
                     "property":  "",
                     "notes":  "56F目で酔いLv1上昇 / 酔いLv3以下の時ドライブゲージ2500回復 / 酔いLv4時ドライブゲージ10000回復"
                 },
                 {
                     "section":  "Unique Attacks",
                     "officialId":  "204",
                     "moveName":  "Falling Star Kick",
                     "moveNameJa":  "落星脚",
                     "command":  "6 + MK",
                     "commandModern":  "6＋中",
                     "startup":  "22",
                     "active":  "22-24",
                     "recovery":  "20",
                     "onHit":  "1",
                     "onBlock":  "-3",
                     "cancel":  "",
                     "damage":  "600",
                     "property":  "中",
                     "notes":  ""
                 },
                 {
                     "section":  "Unique Attacks",
                     "officialId":  "205",
                     "moveName":  "Hermit\u0027s Elbow",
                     "moveNameJa":  "仙姑肘",
                     "command":  "4 + HP",
                     "commandModern":  "4＋強",
                     "startup":  "18",
                     "active":  "18-21",
                     "recovery":  "20",
                     "onHit":  "1",
                     "onBlock":  "-3",
                     "cancel":  "CRITICAL",
                     "damage":  "800",
                     "property":  "上",
                     "notes":  ""
                 },
                 {
                     "section":  "Unique Attacks",
                     "officialId":  "206",
                     "moveName":  "Senei Kick",
                     "moveNameJa":  "旋影脚",
                     "command":  "6 + HK",
                     "commandModern":  "6＋強",
                     "startup":  "16",
                     "active":  "16-18",
                     "recovery":  "20",
                     "onHit":  "3",
                     "onBlock":  "-3",
                     "cancel":  "CRITICAL",
                     "damage":  "900",
                     "property":  "上",
                     "notes":  ""
                 },
                 {
                     "section":  "Unique Attacks",
                     "officialId":  "207",
                     "moveName":  "Bitter Strikes(1)",
                     "moveNameJa":  "鋭鍾打（1段目）",
                     "command":  "（酔いLv1以上）LP",
                     "commandModern":  "（酔いLv1以上）弱",
                     "startup":  "5",
                     "active":  "5-7",
                     "recovery":  "9",
                     "onHit":  "2",
                     "onBlock":  "-3",
                     "cancel":  "SPECIAL_MOVE, D_RUSH_CANCEL, LP_TC1",
                     "damage":  "300",
                     "property":  "上",
                     "notes":  "酔いLv1以上で発動可能"
                 },
                 {
                     "section":  "Unique Attacks",
                     "officialId":  "208",
                     "moveName":  "Bitter Strikes(2)",
                     "moveNameJa":  "鋭鍾打（2段目）",
                     "command":  "（酔いLv1以上）LP\u003eLK",
                     "commandModern":  "（酔いLv1以上）弱＞弱",
                     "startup":  "6",
                     "active":  "6-7",
                     "recovery":  "16",
                     "onHit":  "-3",
                     "onBlock":  "-8",
                     "cancel":  "LP_TC2",
                     "damage":  "200",
                     "property":  "上",
                     "notes":  "酔いLv1以上で発動可能"
                 },
                 {
                     "section":  "Unique Attacks",
                     "officialId":  "208",
                     "moveName":  "Bitter Strikes(3)",
                     "moveNameJa":  "鋭鍾打（3段目）",
                     "command":  "（酔いLv1以上）LP\u003eLK\u003eMP",
                     "commandModern":  "（酔いLv1以上）弱＞弱＞弱",
                     "startup":  "8",
                     "active":  "8-10",
                     "recovery":  "21",
                     "onHit":  "-1",
                     "onBlock":  "-10",
                     "cancel":  "SPECIAL_MOVE, D_RUSH_CANCEL",
                     "damage":  "500",
                     "property":  "上",
                     "notes":  "酔いLv1以上で発動可能 / ※ガード時硬直2F増加"
                 },
                 {
                     "section":  "Unique Attacks",
                     "officialId":  "209",
                     "moveName":  "Full Moon Kick(1)",
                     "moveNameJa":  "円月脚（1段目）",
                     "command":  "6 + MK",
                     "commandModern":  "",
                     "startup":  "22",
                     "active":  "22-24",
                     "recovery":  "20",
                     "onHit":  "1",
                     "onBlock":  "-3",
                     "cancel":  "Nomal_Zurasi_Cancel",
                     "damage":  "600",
                     "property":  "中",
                     "notes":  ""
                 },
                 {
                     "section":  "Unique Attacks",
                     "officialId":  "210",
                     "moveName":  "Full Moon Kick(2)",
                     "moveNameJa":  "円月脚（2段目）",
                     "command":  "（酔いLv2以上）6+MK\u003eMK",
                     "commandModern":  "（酔いLv2以上）6＋中＞中",
                     "startup":  "15",
                     "active":  "15-17, 23-24",
                     "recovery":  "28",
                     "onHit":  "D",
                     "onBlock":  "-14",
                     "cancel":  "6MK_MK_P_TC",
                     "damage":  "400",
                     "property":  "上",
                     "notes":  "酔いLv2以上で発動可能"
                 },
                 {
                     "section":  "Unique Attacks",
                     "officialId":  "211",
                     "moveName":  "Full Moon Kick(3)",
                     "moveNameJa":  "円月脚（3段目）",
                     "command":  "（酔いLv2以上）6+MK\u003eMK\u003eLP | MP | HP",
                     "commandModern":  "（酔いLv2以上）6＋中＞中＞中",
                     "startup":  "",
                     "active":  "",
                     "recovery":  "",
                     "onHit":  "",
                     "onBlock":  "",
                     "cancel":  "",
                     "damage":  "0",
                     "property":  "",
                     "notes":  "酔いLv2以上で発動可能 / 54F目で酔いLv1上昇 / 酔いLv3以下の時ドライブゲージ5000回復 / 酔いLv4時ドライブゲージ10000回復"
                 },
                 {
                     "section":  "Unique Attacks",
                     "officialId":  "212",
                     "moveName":  "Intoxicated Assault(1)",
                     "moveNameJa":  "酩酊襲（1段目）",
                     "command":  "（酔いLv3以上）4 + HP",
                     "commandModern":  "（酔いLv3以上）4＋強",
                     "startup":  "18",
                     "active":  "18-21",
                     "recovery":  "21",
                     "onHit":  "1",
                     "onBlock":  "-3",
                     "cancel":  "4HP_HP, CRITICAL",
                     "damage":  "800",
                     "property":  "上",
                     "notes":  "酔いLv3以上で発動可能"
                 },
                 {
                     "section":  "Unique Attacks",
                     "officialId":  "213",
                     "moveName":  "Intoxicated Assault(2)",
                     "moveNameJa":  "酩酊襲（2段目）",
                     "command":  "（酔いLv3以上）4 + HP\u003eHP",
                     "commandModern":  "（酔いLv3以上）4＋強＞強",
                     "startup":  "21",
                     "active":  "21-24",
                     "recovery":  "20",
                     "onHit":  "1",
                     "onBlock":  "-11",
                     "cancel":  "4HP_HP_HK, CRITICAL",
                     "damage":  "600",
                     "property":  "上",
                     "notes":  "酔いLv3以上で発動可能"
                 },
                 {
                     "section":  "Unique Attacks",
                     "officialId":  "214",
                     "moveName":  "Intoxicated Assault(3)",
                     "moveNameJa":  "酩酊襲（3段目）",
                     "command":  "（酔いLv3以上）4 + HP\u003eHP\u003eHK",
                     "commandModern":  "（酔いLv3以上）4＋強＞強＞強",
                     "startup":  "21",
                     "active":  "21-23",
                     "recovery":  "37",
                     "onHit":  "D",
                     "onBlock":  "-20",
                     "cancel":  "",
                     "damage":  "800",
                     "property":  "上",
                     "notes":  "酔いLv3以上で発動可能"
                 },
                 {
                     "section":  "Unique Attacks",
                     "officialId":  "215",
                     "moveName":  "Ransui Haze(1)",
                     "moveNameJa":  "乱酔旋（1段目）",
                     "command":  "（酔いLv4以上）6 + HK",
                     "commandModern":  "（酔いLv4以上）6＋強",
                     "startup":  "16",
                     "active":  "16-19",
                     "recovery":  "19",
                     "onHit":  "3",
                     "onBlock":  "-3",
                     "cancel":  "6HK_4HK_TC, CRITICAL",
                     "damage":  "900",
                     "property":  "上",
                     "notes":  ""
                 },
                 {
                     "section":  "Unique Attacks",
                     "officialId":  "216",
                     "moveName":  "Ransui Haze(2)",
                     "moveNameJa":  "乱酔旋（2段目）",
                     "command":  "（酔いLv4以上）6+HK\u003e4 + HK",
                     "commandModern":  "（酔いLv4以上）6＋強\u003e4＋強",
                     "startup":  "",
                     "active":  "",
                     "recovery":  "",
                     "onHit":  "",
                     "onBlock":  "",
                     "cancel":  "6HK_4HK_1st_HP",
                     "damage":  "0",
                     "property":  "",
                     "notes":  "酔いLv4で発動可能 / 空振り時も派生可能 / 動作中攻撃ボタンを入力するタイミングによって派生技の内容が変化する / 6-25F　乱酔旋1へ派生可能 / 31-55F　乱酔旋2へ派生可能 / 63-80F　乱酔旋3へ派生可能"
                 },
                 {
                     "section":  "Unique Attacks",
                     "officialId":  "217",
                     "moveName":  "Ransui Haze(3rd hit / immediate)",
                     "moveNameJa":  "乱酔旋（3段目/即派生）",
                     "command":  "（酔いLv4以上）6+HK\u003e4 + HK\u003eLP | MP | HP",
                     "commandModern":  "（酔いLv4以上）6＋強\u003e4＋強＞攻撃",
                     "startup":  "14",
                     "active":  "14-18",
                     "recovery":  "28",
                     "onHit":  "D",
                     "onBlock":  "-13",
                     "cancel":  "SPECIAL_MOVE, D_RUSH_CANCEL",
                     "damage":  "850",
                     "property":  "上",
                     "notes":  "酔いLv4で発動可能"
                 },
                 {
                     "section":  "Unique Attacks",
                     "officialId":  "218",
                     "moveName":  "Ransui Haze(3rd hit / delayed)",
                     "moveNameJa":  "乱酔旋（3段目/ディレイ派生）",
                     "command":  "（酔いLv4以上）6+HK\u003e4 + HK\u003eLP | MP | HP",
                     "commandModern":  "（酔いLv4以上）6＋強\u003e4＋強\u003e攻撃",
                     "startup":  "4",
                     "active":  "4-5, 14-15, 27-28",
                     "recovery":  "27",
                     "onHit":  "D",
                     "onBlock":  "-9",
                     "cancel":  "SPECIAL_MOVE, D_RUSH_CANCEL",
                     "damage":  "1200",
                     "property":  "上",
                     "notes":  "酔いLv4で発動可能"
                 },
                 {
                     "section":  "Unique Attacks",
                     "officialId":  "219",
                     "moveName":  "Ransui Haze(3rd hit / longest possible delay)",
                     "moveNameJa":  "乱酔旋（3段目/大幅ディレイ派生）",
                     "command":  "（酔いLv4以上）6+HK\u003e4 + HK\u003eLP | MP | HP",
                     "commandModern":  "（酔いLv4以上）6＋強\u003e4＋強\u003e攻撃",
                     "startup":  "",
                     "active":  "",
                     "recovery":  "",
                     "onHit":  "",
                     "onBlock":  "",
                     "cancel":  "",
                     "damage":  "0",
                     "property":  "",
                     "notes":  "酔いLv4で発動可能 / ドライブゲージ10000回復"
                 },
                 {
                     "section":  "Special Moves",
                     "officialId":  "300",
                     "moveName":  "The Devil Inside",
                     "moveNameJa":  "魔身",
                     "command":  "5252 + LP | MP | HP",
                     "commandModern":  "5252＋攻撃",
                     "startup":  "",
                     "active":  "",
                     "recovery":  "",
                     "onHit":  "",
                     "onBlock":  "",
                     "cancel":  "",
                     "damage":  "0",
                     "property":  "",
                     "notes":  "49F目で酔いLv1上昇 / 酔いLv4時ドライブゲージ5000回復 / ボタンホールドで動作継続を行い、ホールドした分だけ酔いLvが上昇する / 1段階ホールドした場合、全体動作が97Fとなる / 酔いLvが上昇すると、上昇したLvに応じてダメージ倍率が増加して、技が解放される / 酔いLv毎のダメージ倍率 / 酔いLv0　90% / 酔いLv1　95% / 酔いLv2　100% / 酔いLv3　105% / 酔いLv4　110% / ※絶唱魔身中は酔いLv4であるが、ダメージ倍率は105%となる"
                 },
                 {
                     "section":  "Special Moves",
                     "officialId":  "301",
                     "moveName":  "L Freeflow Strikes(1)",
                     "moveNameJa":  "弱 流酔拳（1段目）",
                     "command":  "236 + LP",
                     "commandModern":  "236＋弱",
                     "startup":  "13",
                     "active":  "13-14",
                     "recovery":  "24",
                     "onHit":  "-1",
                     "onBlock":  "-6",
                     "cancel":  "SUPER_CANCEL_Lv3, RYUSUIKEN_2DANME_L, RYUSUIKEN_2DANME_L, RYUSUI_KYAKU_2DANME_L",
                     "damage":  "350",
                     "property":  "上",
                     "notes":  ""
                 },
                 {
                     "section":  "Special Moves",
                     "officialId":  "302",
                     "moveName":  "[Drink level 4]L Freeflow Strikes(1)",
                     "moveNameJa":  "[酔いレベル4]弱 流酔拳（1段目）",
                     "command":  "236 + LP",
                     "commandModern":  "236＋弱",
                     "startup":  "13",
                     "active":  "13-14,24-26",
                     "recovery":  "19",
                     "onHit":  "1",
                     "onBlock":  "-3",
                     "cancel":  "SUPER_CANCEL_Lv3, RYUSUIKEN_YoiLv4_2DANME, RYUSUIKEN_YoiLv4_2DANME, RYUSUI_KYAKU_2DANME_L",
                     "damage":  "400",
                     "property":  "上",
                     "notes":  "酔いLv4で発動可能"
                 },
                 {
                     "section":  "Special Moves",
                     "officialId":  "303",
                     "moveName":  "M Freeflow Strikes(1)",
                     "moveNameJa":  "中 流酔拳（1段目）",
                     "command":  "236 + MP",
                     "commandModern":  "236＋中/5+SP",
                     "startup":  "16",
                     "active":  "16-17",
                     "recovery":  "24",
                     "onHit":  "-1",
                     "onBlock":  "-6",
                     "cancel":  "SUPER_CANCEL_Lv3, RYUSUIKEN_2DANME_M, RYUSUIKEN_2DANME_M, RYUSUI_KYAKU_2DANME_M",
                     "damage":  "400",
                     "property":  "上",
                     "notes":  ""
                 },
                 {
                     "section":  "Special Moves",
                     "officialId":  "304",
                     "moveName":  "[Drink level 4]M Freeflow Strikes(1)",
                     "moveNameJa":  "[酔いレベル4]中 流酔拳（1段目）",
                     "command":  "236 + MP",
                     "commandModern":  "236＋中/5+SP",
                     "startup":  "16",
                     "active":  "16-17,27-29",
                     "recovery":  "19",
                     "onHit":  "1",
                     "onBlock":  "-3",
                     "cancel":  "SUPER_CANCEL_Lv3, RYUSUIKEN_YoiLv4_2DANME, RYUSUIKEN_YoiLv4_2DANME, RYUSUI_KYAKU_2DANME_M",
                     "damage":  "500",
                     "property":  "上",
                     "notes":  "酔いLv4で発動可能"
                 },
                 {
                     "section":  "Special Moves",
                     "officialId":  "305",
                     "moveName":  "H Freeflow Strikes(1)",
                     "moveNameJa":  "強 流酔拳（1段目）",
                     "command":  "236 + HP",
                     "commandModern":  "236＋強",
                     "startup":  "19",
                     "active":  "19-20",
                     "recovery":  "24",
                     "onHit":  "-1",
                     "onBlock":  "-6",
                     "cancel":  "SUPER_CANCEL_Lv3, RYUSUIKEN_2DANME_H, RYUSUI_KYAKU_2DANME_H, RYUSUIKEN_2DANME_H",
                     "damage":  "450",
                     "property":  "上",
                     "notes":  ""
                 },
                 {
                     "section":  "Special Moves",
                     "officialId":  "306",
                     "moveName":  "[Drink level 4]H Freeflow Strikes(1)",
                     "moveNameJa":  "[酔いレベル4]強 流酔拳（1段目）",
                     "command":  "236 + HP",
                     "commandModern":  "236＋強",
                     "startup":  "19",
                     "active":  "19-20,30-32",
                     "recovery":  "19",
                     "onHit":  "1",
                     "onBlock":  "-3",
                     "cancel":  "SUPER_CANCEL_Lv3, RYUSUIKEN_YoiLv4_2DANME, RYUSUI_KYAKU_2DANME_H, RYUSUIKEN_YoiLv4_2DANME",
                     "damage":  "600",
                     "property":  "上",
                     "notes":  "酔いLv4で発動可能"
                 },
                 {
                     "section":  "Special Moves",
                     "officialId":  "307",
                     "moveName":  "OD Freeflow Strikes(1)",
                     "moveNameJa":  "OD 流酔拳（1段目）",
                     "command":  "236 + LPMPHP",
                     "commandModern":  "236＋攻撃二つ/AUTO＋SP",
                     "startup":  "13",
                     "active":  "13-14",
                     "recovery":  "24",
                     "onHit":  "1",
                     "onBlock":  "-3",
                     "cancel":  "SUPER_CANCEL_Lv2, RYUSUIKEN_2DANME_EX, RYUSUIKEN_2DANME_EX, RYUSUI_KYAKU_2DANME_EX",
                     "damage":  "450",
                     "property":  "上",
                     "notes":  ""
                 },
                 {
                     "section":  "Special Moves",
                     "officialId":  "308",
                     "moveName":  "[Drink level 4]OD Freeflow Strikes(1)",
                     "moveNameJa":  "[酔いレベル4]OD 流酔拳（1段目）",
                     "command":  "236 + LPMPHP",
                     "commandModern":  "236＋攻撃二つ/AUTO＋SP",
                     "startup":  "13",
                     "active":  "16-17,24-26",
                     "recovery":  "19",
                     "onHit":  "3",
                     "onBlock":  "-3",
                     "cancel":  "SUPER_CANCEL_Lv2, RYUSUIKEN_EX_YoiLv4_2DANME, RYUSUIKEN_EX_YoiLv4_2DANME, RYUSUI_KYAKU_2DANME_EX",
                     "damage":  "600",
                     "property":  "上",
                     "notes":  "酔いLv4で発動可能"
                 },
                 {
                     "section":  "Special Moves",
                     "officialId":  "309",
                     "moveName":  "L Freeflow Strikes(2)",
                     "moveNameJa":  "弱 流酔拳（2段目）",
                     "command":  "236 + LP\u003e6 + LP | MP | HP",
                     "commandModern":  "236＋弱\u003e6＋攻撃",
                     "startup":  "13",
                     "active":  "13-14",
                     "recovery":  "28",
                     "onHit":  "-3",
                     "onBlock":  "-13",
                     "cancel":  "RYUSUIKEN_3DANME_L, RYUSUIKEN_3DANME_L",
                     "damage":  "350",
                     "property":  "上",
                     "notes":  "空振り時も派生可能"
                 },
                 {
                     "section":  "Special Moves",
                     "officialId":  "310",
                     "moveName":  "M Freeflow Strikes(2)",
                     "moveNameJa":  "中 流酔拳（2段目）",
                     "command":  "236 + MP\u003e6 + LP | MP | HP",
                     "commandModern":  "236＋中＞6＋攻撃/5+SP＞SP",
                     "startup":  "16",
                     "active":  "16-17",
                     "recovery":  "28",
                     "onHit":  "-3",
                     "onBlock":  "-11",
                     "cancel":  "RYUSUIKEN_3DANME_M, RYUSUIKEN_3DANME_M",
                     "damage":  "400",
                     "property":  "上",
                     "notes":  "空振り時も派生可能"
                 },
                 {
                     "section":  "Special Moves",
                     "officialId":  "311",
                     "moveName":  "H Freeflow Strikes(2)",
                     "moveNameJa":  "強 流酔拳（2段目）",
                     "command":  "236 + HP\u003e6 + LP | MP | HP",
                     "commandModern":  "236＋強＞6＋攻撃",
                     "startup":  "19",
                     "active":  "19-20",
                     "recovery":  "28",
                     "onHit":  "-3",
                     "onBlock":  "-9",
                     "cancel":  "RYUSUIKEN_3DANME_H, RYUSUIKEN_3DANME_H",
                     "damage":  "450",
                     "property":  "上",
                     "notes":  "空振り時も派生可能"
                 },
                 {
                     "section":  "Special Moves",
                     "officialId":  "312",
                     "moveName":  "[Drink level 4]Freeflow Strikes(2)",
                     "moveNameJa":  "[酔いレベル4]流酔拳（2段目）",
                     "command":  "236 + LP | MP | HP\u003e6 + LP | MP | HP",
                     "commandModern":  "236＋攻撃＞6＋攻撃/5+SP＞SP",
                     "startup":  "15",
                     "active":  "15-16, 22-23",
                     "recovery":  "27",
                     "onHit":  "-2",
                     "onBlock":  "-10",
                     "cancel":  "RYUSUIKEN_YoiLv4_3DANME, RYUSUIKEN_YoiLv4_3DANME",
                     "damage":  "450",
                     "property":  "上",
                     "notes":  "酔いLv4で発動可能"
                 },
                 {
                     "section":  "Special Moves",
                     "officialId":  "313",
                     "moveName":  "OD Freeflow Strikes(2)",
                     "moveNameJa":  "OD 流酔拳（2段目）",
                     "command":  "236 + LPMPHP\u003e6 + LP | MP | HP",
                     "commandModern":  "236＋攻撃二つ＞6＋攻撃/AUTO＋SP\u003eSP",
                     "startup":  "13",
                     "active":  "13-14",
                     "recovery":  "28",
                     "onHit":  "-3",
                     "onBlock":  "-9",
                     "cancel":  "RYUSUIKEN_3DANME_EX, RYUSUIKEN_3DANME_EX",
                     "damage":  "450",
                     "property":  "上",
                     "notes":  "空振り時も派生可能"
                 },
                 {
                     "section":  "Special Moves",
                     "officialId":  "314",
                     "moveName":  "[Drink level 4]OD Freeflow Strikes(2)",
                     "moveNameJa":  "[酔いレベル4]OD 流酔拳（2段目）",
                     "command":  "236 + LPMPHP\u003e6 + LP | MP | HP",
                     "commandModern":  "236＋攻撃二つ＞6＋攻撃/AUTO＋SP＞SP",
                     "startup":  "15",
                     "active":  "15-16, 22-23",
                     "recovery":  "27",
                     "onHit":  "-2",
                     "onBlock":  "-10",
                     "cancel":  "RYUSUIKEN_EX_YoiLv4_3DANME, RYUSUIKEN_EX_YoiLv4_3DANME",
                     "damage":  "500",
                     "property":  "上",
                     "notes":  "酔いLv4で発動可能"
                 },
                 {
                     "section":  "Special Moves",
                     "officialId":  "315",
                     "moveName":  "L Freeflow Strikes(3)",
                     "moveNameJa":  "弱 流酔拳（3段目）",
                     "command":  "236 + LP\u003e6 + LP | MP | HP\u003e6 + LP | MP | HP",
                     "commandModern":  "236＋弱\u003e6＋攻撃＞6+攻撃",
                     "startup":  "13",
                     "active":  "13-14",
                     "recovery":  "30",
                     "onHit":  "D",
                     "onBlock":  "-17",
                     "cancel":  "",
                     "damage":  "550",
                     "property":  "上",
                     "notes":  "空振り時も派生可能"
                 },
                 {
                     "section":  "Special Moves",
                     "officialId":  "316",
                     "moveName":  "M Freeflow Strikes(3)",
                     "moveNameJa":  "中 流酔拳（3段目）",
                     "command":  "236 + MP\u003e6 + LP | MP | HP\u003e6 + LP | MP | HP",
                     "commandModern":  "236＋中＞6＋攻撃＞6+攻撃/5+SP＞SP＞SP",
                     "startup":  "16",
                     "active":  "16-17",
                     "recovery":  "30",
                     "onHit":  "D",
                     "onBlock":  "-15",
                     "cancel":  "",
                     "damage":  "600",
                     "property":  "上",
                     "notes":  "空振り時も派生可能"
                 },
                 {
                     "section":  "Special Moves",
                     "officialId":  "317",
                     "moveName":  "H Freeflow Strikes(3)",
                     "moveNameJa":  "強 流酔拳（3段目）",
                     "command":  "236 + HP\u003e6 + LP | MP | HP\u003e6 + LP | MP | HP",
                     "commandModern":  "236＋強＞6＋攻撃＞6＋攻撃",
                     "startup":  "19",
                     "active":  "19-20",
                     "recovery":  "30",
                     "onHit":  "D",
                     "onBlock":  "-13",
                     "cancel":  "",
                     "damage":  "650",
                     "property":  "上",
                     "notes":  "空振り時も派生可能"
                 },
                 {
                     "section":  "Special Moves",
                     "officialId":  "318",
                     "moveName":  "[Drink level 4]Freeflow Strikes(3)",
                     "moveNameJa":  "[酔いレベル4]流酔拳（3段目）",
                     "command":  "236 + LP | MP | HP\u003e6 + LP | MP | HP\u003e6 + LP | MP | HP",
                     "commandModern":  "236＋攻撃＞6＋攻撃＞6＋攻撃/5+SP＞SP＞SP",
                     "startup":  "16",
                     "active":  "16-17,22-23, 38-40",
                     "recovery":  "28",
                     "onHit":  "D",
                     "onBlock":  "-14",
                     "cancel":  "",
                     "damage":  "600",
                     "property":  "上",
                     "notes":  "酔いLv4で発動可能"
                 },
                 {
                     "section":  "Special Moves",
                     "officialId":  "319",
                     "moveName":  "OD Freeflow Strikes(3)",
                     "moveNameJa":  "OD 流酔拳（3段目）",
                     "command":  "236 + LPMPHP\u003e6 + LP | MP | HP\u003e6 + LP | MP | HP",
                     "commandModern":  "236＋攻撃二つ＞6＋攻撃＞6＋攻撃/AUTO＋SP＞SP＞SP",
                     "startup":  "13",
                     "active":  "13-14",
                     "recovery":  "30",
                     "onHit":  "D",
                     "onBlock":  "-13",
                     "cancel":  "",
                     "damage":  "750",
                     "property":  "上",
                     "notes":  "空振り時も派生可能"
                 },
                 {
                     "section":  "Special Moves",
                     "officialId":  "320",
                     "moveName":  "[Drink level 4]OD Freeflow Strikes(3)",
                     "moveNameJa":  "[酔いレベル4]OD 流酔拳（3段目）",
                     "command":  "236 + LPMPHP\u003e6 + LP | MP | HP\u003e6 + LP | MP | HP",
                     "commandModern":  "236＋攻撃二つ＞6＋攻撃＞6＋攻撃/AUTO＋SP＞SP＞SP",
                     "startup":  "16",
                     "active":  "16-17,22-23, 38-40",
                     "recovery":  "28",
                     "onHit":  "D",
                     "onBlock":  "-14",
                     "cancel":  "",
                     "damage":  "700",
                     "property":  "上",
                     "notes":  "酔いLv4で発動可能"
                 },
                 {
                     "section":  "Special Moves",
                     "officialId":  "321",
                     "moveName":  "L Freeflow Kicks(2)",
                     "moveNameJa":  "弱 流酔脚（2段目）",
                     "command":  "236 + LP\u003e6 + LK | MK | HK",
                     "commandModern":  "236＋弱＞4＋攻撃",
                     "startup":  "14",
                     "active":  "14-15",
                     "recovery":  "32",
                     "onHit":  "-7",
                     "onBlock":  "-15",
                     "cancel":  "RYUSUI_KYAKU_3DANME_L",
                     "damage":  "250",
                     "property":  "上",
                     "notes":  ""
                 },
                 {
                     "section":  "Special Moves",
                     "officialId":  "322",
                     "moveName":  "M Freeflow Kicks(2)",
                     "moveNameJa":  "中 流酔脚（2段目）",
                     "command":  "236 + MP\u003e6 + LK | MK | HK",
                     "commandModern":  "236＋中＞4＋攻撃/SP＞4＋SP",
                     "startup":  "17",
                     "active":  "17-18",
                     "recovery":  "32",
                     "onHit":  "-7",
                     "onBlock":  "-15",
                     "cancel":  "RYUSUI_KYAKU_3DANME_M",
                     "damage":  "300",
                     "property":  "上",
                     "notes":  ""
                 },
                 {
                     "section":  "Special Moves",
                     "officialId":  "323",
                     "moveName":  "H Freeflow Kicks(2)",
                     "moveNameJa":  "強 流酔脚（2段目）",
                     "command":  "236 + HP\u003e6 + LK | MK | HK",
                     "commandModern":  "236＋強＞4＋攻撃",
                     "startup":  "20",
                     "active":  "20-21",
                     "recovery":  "32",
                     "onHit":  "-7",
                     "onBlock":  "-15",
                     "cancel":  "RYUSUI_KYAKU_3DANME_H",
                     "damage":  "300",
                     "property":  "上",
                     "notes":  ""
                 },
                 {
                     "section":  "Special Moves",
                     "officialId":  "324",
                     "moveName":  "OD Freeflow Kicks(2)",
                     "moveNameJa":  "OD 流酔脚（2段目）",
                     "command":  "236 + LPMPHP\u003e6 + LK | MK | HK",
                     "commandModern":  "236＋攻撃二つ＞4＋攻撃/AUTO＋SP＞4＋SP",
                     "startup":  "14",
                     "active":  "14-15",
                     "recovery":  "32",
                     "onHit":  "-7",
                     "onBlock":  "-15",
                     "cancel":  "RYUSUI_KYAKU_3DANME_EX",
                     "damage":  "350",
                     "property":  "上",
                     "notes":  ""
                 },
                 {
                     "section":  "Special Moves",
                     "officialId":  "325",
                     "moveName":  "L Freeflow Kicks(3)",
                     "moveNameJa":  "弱 流酔脚（3段目）",
                     "command":  "236 + LP\u003e6 + LK | MK | HK\u003e6 + LK | MK | HK",
                     "commandModern":  "236＋弱＞4＋攻撃＞4＋攻撃",
                     "startup":  "18",
                     "active":  "18-19",
                     "recovery":  "64",
                     "onHit":  "D",
                     "onBlock":  "-49",
                     "cancel":  "",
                     "damage":  "450",
                     "property":  "上",
                     "notes":  "55F目で酔いLv1上昇 / 酔いLv3以下の時ドライブゲージ5000回復 / 酔いLv4時ドライブゲージ10000回復"
                 },
                 {
                     "section":  "Special Moves",
                     "officialId":  "326",
                     "moveName":  "M Freeflow Kicks(3)",
                     "moveNameJa":  "中 流酔脚（3段目）",
                     "command":  "236 + MP\u003e6 + LK | MK | HK\u003e6 + LK | MK | HK",
                     "commandModern":  "236＋中＞4＋攻撃＞4＋攻撃/SP＞4＋SP＞4＋SP",
                     "startup":  "21",
                     "active":  "21-22",
                     "recovery":  "64",
                     "onHit":  "D",
                     "onBlock":  "-49",
                     "cancel":  "",
                     "damage":  "500",
                     "property":  "上",
                     "notes":  "59F目で酔いLv1上昇 / 酔いLv3以下の時ドライブゲージ5000回復 / 酔いLv4時ドライブゲージ10000回復"
                 },
                 {
                     "section":  "Special Moves",
                     "officialId":  "327",
                     "moveName":  "H Freeflow Kicks(3)",
                     "moveNameJa":  "強 流酔脚（3段目）",
                     "command":  "236 + HP\u003e6 + LK | MK | HK\u003e6 + LK | MK | HK",
                     "commandModern":  "236＋強＞4＋攻撃＞4＋攻撃",
                     "startup":  "24",
                     "active":  "24-25",
                     "recovery":  "64",
                     "onHit":  "D",
                     "onBlock":  "-49",
                     "cancel":  "",
                     "damage":  "550",
                     "property":  "上",
                     "notes":  "62F目で酔いLv1上昇 / 酔いLv3以下の時ドライブゲージ5000回復 / 酔いLv4時ドライブゲージ10000回復"
                 },
                 {
                     "section":  "Special Moves",
                     "officialId":  "328",
                     "moveName":  "OD Freeflow Kicks(3)",
                     "moveNameJa":  "OD 流酔脚（3段目）",
                     "command":  "236 + LPMPHP\u003e6 + LK | MK | HK\u003e6 + LK | MK | HK",
                     "commandModern":  "236＋攻撃二つ＞4＋攻撃＞4＋攻撃/AUTO＋SP\u003e4＋SP＞4＋SP",
                     "startup":  "18",
                     "active":  "18-19",
                     "recovery":  "64",
                     "onHit":  "D",
                     "onBlock":  "-49",
                     "cancel":  "",
                     "damage":  "600",
                     "property":  "上",
                     "notes":  "56F目で酔いLv1上昇 / 酔いLv3以下の時ドライブゲージ5000回復 / 酔いLv4時ドライブゲージ10000回復"
                 },
                 {
                     "section":  "Special Moves",
                     "officialId":  "329",
                     "moveName":  "L Swagger Step",
                     "moveNameJa":  "弱 酔疾歩",
                     "command":  "214 + LP",
                     "commandModern":  "214＋弱",
                     "startup":  "17",
                     "active":  "17-25",
                     "recovery":  "17",
                     "onHit":  "D",
                     "onBlock":  "-6",
                     "cancel":  "SUPER_CANCEL_Lv3, SIPPOSENSHO_NOMAL",
                     "damage":  "900",
                     "property":  "上",
                     "notes":  ""
                 },
                 {
                     "section":  "Special Moves",
                     "officialId":  "330",
                     "moveName":  "M Swagger Step",
                     "moveNameJa":  "中 酔疾歩",
                     "command":  "214 + MP",
                     "commandModern":  "214＋中",
                     "startup":  "20",
                     "active":  "20-28",
                     "recovery":  "17",
                     "onHit":  "D",
                     "onBlock":  "-6",
                     "cancel":  "SUPER_CANCEL_Lv3, SIPPOSENSHO_NOMAL",
                     "damage":  "1000",
                     "property":  "上",
                     "notes":  ""
                 },
                 {
                     "section":  "Special Moves",
                     "officialId":  "331",
                     "moveName":  "H Swagger Step",
                     "moveNameJa":  "強 酔疾歩",
                     "command":  "214 + HP",
                     "commandModern":  "214＋強",
                     "startup":  "25",
                     "active":  "25-33",
                     "recovery":  "16",
                     "onHit":  "D",
                     "onBlock":  "-3",
                     "cancel":  "SUPER_CANCEL_Lv3, SIPPOSENSHO_NOMAL",
                     "damage":  "1200",
                     "property":  "上",
                     "notes":  ""
                 },
                 {
                     "section":  "Special Moves",
                     "officialId":  "332",
                     "moveName":  "OD Swagger Step",
                     "moveNameJa":  "OD 酔疾歩",
                     "command":  "214 + LPMPHP",
                     "commandModern":  "214＋攻撃二つ",
                     "startup":  "20",
                     "active":  "20-28",
                     "recovery":  "15",
                     "onHit":  "D",
                     "onBlock":  "-1",
                     "cancel":  "SUPER_CANCEL_Lv2, SIPPOSENSHO_EX",
                     "damage":  "1100",
                     "property":  "上",
                     "notes":  "パニッシュカウンター時のみ壁やられ"
                 },
                 {
                     "section":  "Special Moves",
                     "officialId":  "333",
                     "moveName":  "L Arrow Kick",
                     "moveNameJa":  "弱 張弓腿",
                     "command":  "626 + LK",
                     "commandModern":  "623＋弱",
                     "startup":  "5",
                     "active":  "5-14, 41-50",
                     "recovery":  "52",
                     "onHit":  "D",
                     "onBlock":  "-45",
                     "cancel":  "",
                     "damage":  "1000",
                     "property":  "上",
                     "notes":  "1-12F　空中判定の打撃・空弾属性に対して無敵 / ※2段目以降は初段ヒット時のみ派生"
                 },
                 {
                     "section":  "Special Moves",
                     "officialId":  "334",
                     "moveName":  "M Arrow Kick",
                     "moveNameJa":  "中 張弓腿",
                     "command":  "626 + MK",
                     "commandModern":  "623＋中",
                     "startup":  "8",
                     "active":  "8-16, 39-43",
                     "recovery":  "51",
                     "onHit":  "D",
                     "onBlock":  "-43",
                     "cancel":  "",
                     "damage":  "1200",
                     "property":  "上",
                     "notes":  "1-14F　空中判定の打撃・空弾属性に対して無敵 / ※2段目以降は初段ヒット時のみ派生"
                 },
                 {
                     "section":  "Special Moves",
                     "officialId":  "335",
                     "moveName":  "H Arrow Kick",
                     "moveNameJa":  "強 張弓腿",
                     "command":  "626 + HK",
                     "commandModern":  "623＋強/6＋SP",
                     "startup":  "10",
                     "active":  "10-18, 41-45, 54-57",
                     "recovery":  "51",
                     "onHit":  "D",
                     "onBlock":  "-43",
                     "cancel":  "",
                     "damage":  "1400",
                     "property":  "上",
                     "notes":  "1-16F　空中判定の打撃・空弾属性に対して無敵 / ※2段目以降は初段ヒット時のみ派生"
                 },
                 {
                     "section":  "Special Moves",
                     "officialId":  "336",
                     "moveName":  "OD Arrow Kick",
                     "moveNameJa":  "OD 張弓腿",
                     "command":  "626 + LKMKHK",
                     "commandModern":  "623＋攻撃二つ/6＋AUTO＋SP",
                     "startup":  "6",
                     "active":  "6-12, 37-38, 50-51",
                     "recovery":  "53",
                     "onHit":  "D",
                     "onBlock":  "-43",
                     "cancel":  "",
                     "damage":  "1500",
                     "property":  "上",
                     "notes":  "1-9F　完全無敵 / 10-12F　空中判定の打撃・空弾属性に対して無敵 / ※2段目以降は初段ヒット時のみ派生"
                 },
                 {
                     "section":  "Special Moves",
                     "officialId":  "337",
                     "moveName":  "L Luminous Dive Kick",
                     "moveNameJa":  "弱 無影蹴",
                     "command":  "（酔いLv1以上）(前ジャンプ中に)214 + LK",
                     "commandModern":  "（酔いLv1以上）(前ジャンプ中に)214＋弱",
                     "startup":  "11",
                     "active":  "11,14-着地まで",
                     "recovery":  "着地後13",
                     "onHit":  "D",
                     "onBlock":  "",
                     "cancel":  "",
                     "damage":  "1000",
                     "property":  "上",
                     "notes":  "酔いLv1以上で発動可能"
                 },
                 {
                     "section":  "Special Moves",
                     "officialId":  "338",
                     "moveName":  "M Luminous Dive Kick",
                     "moveNameJa":  "中 無影蹴",
                     "command":  "（酔いLv1以上）(前ジャンプ中に)214 + MK",
                     "commandModern":  "（酔いLv1以上）(前ジャンプ中に)214＋中/（酔いLv1以上）(前ジャンプ中に)SP",
                     "startup":  "11",
                     "active":  "11,14-着地まで",
                     "recovery":  "着地後13",
                     "onHit":  "D",
                     "onBlock":  "",
                     "cancel":  "",
                     "damage":  "1000",
                     "property":  "上",
                     "notes":  "酔いLv1以上で発動可能"
                 },
                 {
                     "section":  "Special Moves",
                     "officialId":  "339",
                     "moveName":  "H Luminous Dive Kick",
                     "moveNameJa":  "強 無影蹴",
                     "command":  "（酔いLv1以上）(前ジャンプ中に)214 + HK",
                     "commandModern":  "（酔いLv1以上）(前ジャンプ中に)214＋強",
                     "startup":  "11",
                     "active":  "11,14-着地まで",
                     "recovery":  "着地後13",
                     "onHit":  "D",
                     "onBlock":  "",
                     "cancel":  "",
                     "damage":  "1000",
                     "property":  "上",
                     "notes":  "酔いLv1以上で発動可能"
                 },
                 {
                     "section":  "Special Moves",
                     "officialId":  "340",
                     "moveName":  "OD Luminous Dive Kick",
                     "moveNameJa":  "OD 無影蹴",
                     "command":  "（酔いLv1以上）(前ジャンプ中に)214 + LKMKHK",
                     "commandModern":  "（酔いLv1以上）(前ジャンプ中に)214＋攻撃二つ/（酔いLv1以上）(前ジャンプ中に)AUTO＋SP",
                     "startup":  "11",
                     "active":  "11,14-着地まで",
                     "recovery":  "着地後13",
                     "onHit":  "D",
                     "onBlock":  "",
                     "cancel":  "",
                     "damage":  "800",
                     "property":  "上",
                     "notes":  "酔いLv1以上で発動可能"
                 },
                 {
                     "section":  "Special Moves",
                     "officialId":  "341",
                     "moveName":  "L Bakkai",
                     "moveNameJa":  "弱 爆廻",
                     "command":  "（酔いLv2以上）236 + LK",
                     "commandModern":  "",
                     "startup":  "18",
                     "active":  "18-19, 22-24, 29-30, 42-43",
                     "recovery":  "24",
                     "onHit":  "D",
                     "onBlock":  "-12",
                     "cancel":  "SUPER_CANCEL_Lv3",
                     "damage":  "1400",
                     "property":  "上",
                     "notes":  "酔いLv2以上で発動可能 / 3-24F　飛び道具に対して無敵 / 最終段のみSA3/CAでキャンセル可能"
                 },
                 {
                     "section":  "Special Moves",
                     "officialId":  "342",
                     "moveName":  "M Bakkai",
                     "moveNameJa":  "中 爆廻",
                     "command":  "（酔いLv2以上）236 + MK",
                     "commandModern":  "（酔いLv2以上）2＋SP",
                     "startup":  "22",
                     "active":  "22-23, 25-26, 30-31, 37-38, 51-52, 58-59",
                     "recovery":  "31",
                     "onHit":  "D",
                     "onBlock":  "-16",
                     "cancel":  "SUPER_CANCEL_Lv3",
                     "damage":  "1600",
                     "property":  "上",
                     "notes":  "酔いLv2以上で発動可能 / 4-26F　飛び道具に対して無敵 / 最終段のみSA3/CAでキャンセル可能"
                 },
                 {
                     "section":  "Special Moves",
                     "officialId":  "343",
                     "moveName":  "H Bakkai",
                     "moveNameJa":  "強 爆廻",
                     "command":  "（酔いLv2以上）236 + HK",
                     "commandModern":  "",
                     "startup":  "25",
                     "active":  "25-27, 34-35, 42-43, 50-51, 65-66, 74-75, 91-92",
                     "recovery":  "32",
                     "onHit":  "D",
                     "onBlock":  "-17",
                     "cancel":  "SUPER_CANCEL_Lv3",
                     "damage":  "1800",
                     "property":  "上",
                     "notes":  "酔いLv2以上で発動可能 / 5-33F　飛び道具に対して無敵 / 最終段のみSA3/CAでキャンセル可能"
                 },
                 {
                     "section":  "Special Moves",
                     "officialId":  "344",
                     "moveName":  "OD Bakkai",
                     "moveNameJa":  "OD 爆廻",
                     "command":  "（酔いLv2以上）236 + LKMKHK",
                     "commandModern":  "（酔いLv2以上）2＋AUTO＋SP",
                     "startup":  "18",
                     "active":  "18-23, 27-28, 37-38, 42-43, 51-52, 60-61, 74-75, 87-88, 93-94, 99-100",
                     "recovery":  "59",
                     "onHit":  "D",
                     "onBlock":  "-43",
                     "cancel":  "SUPER_CANCEL_Lv2",
                     "damage":  "2000",
                     "property":  "上",
                     "notes":  "3-28F　飛び道具に対して無敵 / 7段目のみSA3/CAでキャンセル可能"
                 },
                 {
                     "section":  "Special Moves",
                     "officialId":  "345",
                     "moveName":  "Tenshin",
                     "moveNameJa":  "点辰",
                     "command":  "（酔いLv3以上）（近距離で）631462146324 + LK | MK | HK",
                     "commandModern":  "（酔いLv3以上）（近距離で）4＋SP",
                     "startup":  "8",
                     "active":  "8-9",
                     "recovery":  "52",
                     "onHit":  "8",
                     "onBlock":  "",
                     "cancel":  "",
                     "damage":  "0",
                     "property":  "投",
                     "notes":  "酔いLv3以上で発動可能 / ※コンボの3段目以降に補正がかかる"
                 },
                 {
                     "section":  "Special Moves",
                     "officialId":  "346",
                     "moveName":  "OD Tenshin",
                     "moveNameJa":  "OD 点辰",
                     "command":  "（酔いLv3以上）（近距離で）631462146324 + LKMKHK",
                     "commandModern":  "（酔いLv3以上）（近距離で）4＋AUTO＋SP",
                     "startup":  "8",
                     "active":  "8-9",
                     "recovery":  "52",
                     "onHit":  "D",
                     "onBlock":  "",
                     "cancel":  "",
                     "damage":  "650",
                     "property":  "投",
                     "notes":  "酔いLv3以上で発動可能 / ヒット時膝崩れ / ■クラシック操作 / パニッシュカウンター時個別ダメージ（784） / ■モダン操作時 / パニッシュカウンター時個別ダメージ（627）"
                 },
                 {
                     "section":  "Special Moves",
                     "officialId":  "347",
                     "moveName":  "Swagger Hermit Punch",
                     "moveNameJa":  "疾歩仙掌",
                     "command":  "（酔いLv4以上）214＋LP|MP|HP\u003e6 + LP | MP | HP",
                     "commandModern":  "（酔いLv4以上）214＋攻撃＞（酔いLv4以上）6＋攻撃",
                     "startup":  "19",
                     "active":  "19-21",
                     "recovery":  "39",
                     "onHit":  "D",
                     "onBlock":  "-23",
                     "cancel":  "SUPER_CANCEL_Lv3",
                     "damage":  "900",
                     "property":  "上",
                     "notes":  "酔いLv4で発動可能"
                 },
                 {
                     "section":  "Special Moves",
                     "officialId":  "348",
                     "moveName":  "OD Swagger Hermit Punch",
                     "moveNameJa":  "OD 疾歩仙掌",
                     "command":  "（酔いLv4以上）214＋LPMPHP\u003e6 + LP | MP | HP",
                     "commandModern":  "（酔いLv4以上）214＋攻撃二つ＞（酔いLv4以上）6＋攻撃",
                     "startup":  "19",
                     "active":  "19-21",
                     "recovery":  "39",
                     "onHit":  "D",
                     "onBlock":  "-23",
                     "cancel":  "SUPER_CANCEL_Lv2",
                     "damage":  "1000",
                     "property":  "上",
                     "notes":  "酔いLv4で発動可能"
                 },
                 {
                     "section":  "Super Arts",
                     "officialId":  "400",
                     "moveName":  "SA1 Breakin\u0027",
                     "moveNameJa":  "SA1 武麗禽",
                     "command":  "23626 | 26236 + LK | MK | HK",
                     "commandModern":  "236236＋弱/N or 6＋強SP",
                     "startup":  "8",
                     "active":  "8-16, 23-27, 34-35, 43-44, 52-53, 60-61, 68-69, 75-76, 106-107, 117-118, 125-126, 132-133",
                     "recovery":  "74※107",
                     "onHit":  "D",
                     "onBlock":  "-60※-93",
                     "cancel":  "GROUND",
                     "damage":  "2200※1850",
                     "property":  "上",
                     "notes":  "1-12　打撃・投げに対して無敵 / 最低保障ダメージ30％ / カウンター/パニッシュカウンターで数値が変動しない / ※動作中に、下方向を入力し続けると性質が変化し、酔いLvが1上昇する。"
                 },
                 {
                     "section":  "Super Arts",
                     "officialId":  "401",
                     "moveName":  "SA2 The Devil\u0027s Song",
                     "moveNameJa":  "SA2 絶唱魔身",
                     "command":  "21424 | 24214 + LP | MP | HP",
                     "commandModern":  "214214＋中/4＋強SP",
                     "startup":  "",
                     "active":  "",
                     "recovery":  "",
                     "onHit":  "",
                     "onBlock":  "",
                     "cancel":  "GROUND",
                     "damage":  "0",
                     "property":  "",
                     "notes":  "発動後、一定時間酔いLv4状態となる / （ただし、ダメージ倍率は105%） / 効果時間900F / 酔いLv4時に発動するとドライブゲージ30000回復"
                 },
                 {
                     "section":  "Super Arts",
                     "officialId":  "402",
                     "moveName":  "SA3 Getsuga Saiho",
                     "moveNameJa":  "SA3 月牙叉炮",
                     "command":  "23626 | 26236 + LP | MP | HP",
                     "commandModern":  "236236＋強/2＋強SP",
                     "startup":  "10",
                     "active":  "10-12, 26-28",
                     "recovery":  "42",
                     "onHit":  "D",
                     "onBlock":  "-27",
                     "cancel":  "GROUND",
                     "damage":  "2600",
                     "property":  "上",
                     "notes":  "1-12F　完全無敵 / 最低保障ダメージ50％ / カウンター/パニッシュカウンターで数値が変動しない / ハードノックダウン / ※必殺技キャンセル時のみ適用"
                 },
                 {
                     "section":  "Super Arts",
                     "officialId":  "403",
                     "moveName":  "CA Getsuga Saiho",
                     "moveNameJa":  "CA 月牙叉炮",
                     "command":  "（体力25%以下で）23626 | 26236 + LP | MP | HP",
                     "commandModern":  "（体力25%以下で）236236＋強/（体力25%以下で）2＋強SP",
                     "startup":  "10",
                     "active":  "10-12, 26-28",
                     "recovery":  "42",
                     "onHit":  "D",
                     "onBlock":  "-27",
                     "cancel":  "GROUND",
                     "damage":  "4500",
                     "property":  "上",
                     "notes":  "1-12F　完全無敵 / 最低保障ダメージ50％ / カウンター/パニッシュカウンターで数値が変動しない / ハードノックダウン / ※必殺技キャンセル時のみ適用"
                 },
                 {
                     "section":  "Throws",
                     "officialId":  "500",
                     "moveName":  "Back Shaver",
                     "moveNameJa":  "背剪手",
                     "command":  "（近距離で）N or 6 + LPLK",
                     "commandModern":  "（近距離で）N or 6 + 弱中",
                     "startup":  "5",
                     "active":  "5-7",
                     "recovery":  "23",
                     "onHit":  "D",
                     "onBlock":  "",
                     "cancel":  "",
                     "damage":  "1200",
                     "property":  "投",
                     "notes":  "パニッシュカウンター時以下の性能変化 / ・ダメージ2040 / ・SAゲージ4000増加 / ・ハードノックダウン / ※動作中ボタンホールドで性質が変化し、酔いLvが1上昇する。"
                 },
                 {
                     "section":  "Throws",
                     "officialId":  "501",
                     "moveName":  "Wheel Punch",
                     "moveNameJa":  "転輪衝",
                     "command":  "（近距離で）4 + LPLK",
                     "commandModern":  "（近距離で）4 + 弱中",
                     "startup":  "5",
                     "active":  "5-7",
                     "recovery":  "23",
                     "onHit":  "D",
                     "onBlock":  "",
                     "cancel":  "",
                     "damage":  "1200",
                     "property":  "投",
                     "notes":  "パニッシュカウンター時以下の性能変化 / ・ダメージ2040 / ・SAゲージ4000増加 / ・ハードノックダウン"
                 },
                 {
                     "section":  "Common Moves",
                     "officialId":  "600",
                     "moveName":  "Forward Dash",
                     "moveNameJa":  "前方ステップ",
                     "command":  "5656 + 6",
                     "commandModern":  "5656 ＋ 6",
                     "startup":  "",
                     "active":  "",
                     "recovery":  "",
                     "onHit":  "",
                     "onBlock":  "",
                     "cancel":  "",
                     "damage":  "0",
                     "property":  "",
                     "notes":  ""
                 },
                 {
                     "section":  "Common Moves",
                     "officialId":  "601",
                     "moveName":  "Backward Dash",
                     "moveNameJa":  "後方ステップ",
                     "command":  "5454 + 4",
                     "commandModern":  "5454 ＋ 4",
                     "startup":  "",
                     "active":  "",
                     "recovery":  "",
                     "onHit":  "",
                     "onBlock":  "",
                     "cancel":  "",
                     "damage":  "0",
                     "property":  "",
                     "notes":  "1-15F　投げ無敵"
                 },
                 {
                     "section":  "Common Moves",
                     "officialId":  "602",
                     "moveName":  "Drive Impact: Vainglory Strike",
                     "moveNameJa":  "ドライブインパクト（独尊撃）",
                     "command":  "HPHK",
                     "commandModern":  "DI",
                     "startup":  "26",
                     "active":  "26-27",
                     "recovery":  "35",
                     "onHit":  "D",
                     "onBlock":  "-3",
                     "cancel":  "",
                     "damage":  "800",
                     "property":  "上",
                     "notes":  "1-27F　 アーマー判定（2回） / パニッシュカウンター、もしくはアーマー成立後にヒットで以下の性能変化 / ・地上ヒット膝崩れ / ・空中ヒットきりもみダウン / ・SAゲージ3000増加"
                 },
                 {
                     "section":  "Common Moves",
                     "officialId":  "603",
                     "moveName":  "Drive Reversal (while blocking): Leg Sweep",
                     "moveNameJa":  "[ガード時]ドライブリバーサル（空掃腿）",
                     "command":  "（ガード中 or ドライブパリィ成立中に）6 ＋ HPHK",
                     "commandModern":  "（ガード中 or ドライブパリィ成立中に）6＋DI",
                     "startup":  "20",
                     "active":  "20-22",
                     "recovery":  "26",
                     "onHit":  "D",
                     "onBlock":  "-6",
                     "cancel":  "",
                     "damage":  "500",
                     "property":  "上",
                     "notes":  "リカバリアブルダメージ / 1-22F完全無敵 / ヒット時硬直が5F増加"
                 },
                 {
                     "section":  "Common Moves",
                     "officialId":  "604",
                     "moveName":  "Drive Reversal (while recovering): Leg Sweep",
                     "moveNameJa":  "[起き上がり時]ドライブリバーサル（空掃腿）",
                     "command":  "（起き上がり時に）6 ＋ HPHK",
                     "commandModern":  "（起き上がり時に）6＋DI",
                     "startup":  "18",
                     "active":  "18-20",
                     "recovery":  "26",
                     "onHit":  "D",
                     "onBlock":  "-6",
                     "cancel":  "",
                     "damage":  "500",
                     "property":  "上",
                     "notes":  "リカバリアブルダメージ / 1-20F 完全無敵 / ヒット時硬直5F増加"
                 },
                 {
                     "section":  "Common Moves",
                     "officialId":  "605",
                     "moveName":  "Drive Parry",
                     "moveNameJa":  "ドライブパリィ",
                     "command":  "MPMK",
                     "commandModern":  "DP",
                     "startup":  "1",
                     "active":  "[※2] 1-12",
                     "recovery":  "33",
                     "onHit":  "",
                     "onBlock":  "",
                     "cancel":  "PARRY",
                     "damage":  "0",
                     "property":  "",
                     "notes":  "※1 動作の4F目からドライブラッシュでキャンセル可 / ※2 ボタンホールドでパリィの持続を延長可 / 硬直部分はガードのみ可 / 動作中常に被パニッシュカウンター判定"
                 },
                 {
                     "section":  "Common Moves",
                     "officialId":  "606",
                     "moveName":  "Perfect Parry (strike)",
                     "moveNameJa":  "ジャストパリィ（打撃）",
                     "command":  "ガード方向 ＋  MPMK",
                     "commandModern":  "ガード方向 ＋  DP",
                     "startup":  "1",
                     "active":  "",
                     "recovery":  "1",
                     "onHit":  "",
                     "onBlock":  "",
                     "cancel":  "",
                     "damage":  "0",
                     "property":  "",
                     "notes":  "相手の攻撃に対応した方向入力を行った状態でパリィを入力し、 / 入力したフレーム、もしくはその次のフレームで攻撃を受けると成立する / （上段/中段攻撃に対して←方向、下段攻撃に対しては↙方向) / 方向が正しくなかった場合は通常のドライブパリィとなり、追加でDゲージが3000増加する / 硬直終了から5Fの間完全無敵 （パリィを継続した場合は無敵にならない） / ジャストパリィを取られた側はキャンセルが出来なくなり、動作終了まで強制パニッシュカウンター"
                 },
                 {
                     "section":  "Common Moves",
                     "officialId":  "607",
                     "moveName":  "Perfect Parry (projectile)",
                     "moveNameJa":  "ジャストパリィ（飛び道具）",
                     "command":  "MPMK",
                     "commandModern":  "DP",
                     "startup":  "1",
                     "active":  "",
                     "recovery":  "10",
                     "onHit":  "",
                     "onBlock":  "",
                     "cancel":  "",
                     "damage":  "0",
                     "property":  "",
                     "notes":  "パリィを入力したフレーム、もしくはその次のフレームで攻撃を受けると成立する / 暗転演出が入らない / ジャストパリィを取られた側はキャンセルが出来なくなり、動作終了まで強制パニッシュカウンター"
                 },
                 {
                     "section":  "Common Moves",
                     "officialId":  "608",
                     "moveName":  "Parry Drive Rush",
                     "moveNameJa":  "パリィドライブラッシュ",
                     "command":  "（ドライブパリィ中に）5656 ＋ MPMK ＋ 6",
                     "commandModern":  "（ドライブパリィ中に）5656＋DP",
                     "startup":  "",
                     "active":  "",
                     "recovery":  "",
                     "onHit":  "",
                     "onBlock":  "",
                     "cancel":  "D_RUSH_KANSEI_KOUGEKI",
                     "damage":  "0",
                     "property":  "",
                     "notes":  "暗転10F / ※動作9F目から攻撃行動にキャンセル可 / 24F目からパリィ以外の行動でキャンセル可"
                 },
                 {
                     "section":  "Common Moves",
                     "officialId":  "609",
                     "moveName":  "Cancel Drive Rush",
                     "moveNameJa":  "キャンセルドライブラッシュ",
                     "command":  "（必殺技キャンセル可能な攻撃ヒット中に）5656 ＋ 6 or (N or 6) + MPMK",
                     "commandModern":  "（必殺技キャンセル可能な攻撃ヒット中に）5656 ＋ 6 or (N or 6) + DP",
                     "startup":  "",
                     "active":  "",
                     "recovery":  "",
                     "onHit":  "",
                     "onBlock":  "",
                     "cancel":  "D_RUSH_KANSEI_KOUGEKI",
                     "damage":  "0",
                     "property":  "",
                     "notes":  "暗転9F / ※動作10F目から攻撃行動にキャンセル可 / 25F目からパリィ以外の行動でキャンセル可"
                 }
             ]
}
